predictiveopt/__init__.py
predictiveopt/algorithm/__init__.py
predictiveopt/algorithm/predictive_hyper_opt_algorithm.py
predictiveopt/models/__init__.py
predictiveopt/models/kmeans.py
predictiveopt/models/linear_regression.py
predictiveopt-0.0.3.dist-info/LICENSE
predictiveopt-0.0.3.dist-info/METADATA
predictiveopt-0.0.3.dist-info/WHEEL
predictiveopt-0.0.3.dist-info/top_level.txt
predictiveopt-0.0.3.dist-info/RECORD
