Metadata-Version: 2.1
Name: predictiveopt
Version: 0.0.3
Summary: Package containing an implementation of the Predictive Hyperparameter Optimisation algorithm.
Home-page: https://github.com/DobromirM/Predictive-Hyperparameter-Optimisation
Author: Dobromir Marinov
Author-email: mr.d.marinov@gmail.com
License: UNKNOWN
Platform: UNKNOWN
Classifier: Programming Language :: Python :: 3
Classifier: License :: OSI Approved :: GNU General Public License (GPL)
Classifier: Operating System :: OS Independent
